{
    "codeToName": {
        "32": "uni0020",
        "33": "uni0021",
        "34": "uni0022",
        "35": "uni0023",
        "36": "uni0024",
        "37": "uni0025",
        "38": "uni0026",
        "39": "uni0027",
        "40": "uni0028",
        "41": "uni0029",
        "42": "uni002a",
        "43": "uni002b",
        "44": "uni002c",
        "45": "uni002d",
        "46": "uni002e",
        "47": "uni002f",
        "48": "uni0030",
        "49": "uni0031",
        "50": "uni0032",
        "51": "uni0033",
        "52": "uni0034",
        "53": "uni0035",
        "54": "uni0036",
        "55": "uni0037",
        "56": "uni0038",
        "57": "uni0039",
        "58": "uni003a",
        "59": "uni003b",
        "60": "uni003c",
        "61": "uni003d",
        "62": "uni003e",
        "63": "uni003f",
        "64": "uni0040",
        "65": "uni0041",
        "66": "uni0042",
        "67": "uni0043",
        "68": "uni0044",
        "69": "uni0045",
        "70": "uni0046",
        "71": "uni0047",
        "72": "uni0048",
        "73": "uni0049",
        "74": "uni004a",
        "75": "uni004b",
        "76": "uni004c",
        "77": "uni004d",
        "78": "uni004e",
        "79": "uni004f",
        "80": "uni0050",
        "81": "uni0051",
        "82": "uni0052",
        "83": "uni0053",
        "84": "uni0054",
        "85": "uni0055",
        "86": "uni0056",
        "87": "uni0057",
        "88": "uni0058",
        "89": "uni0059",
        "90": "uni005a",
        "91": "uni005b",
        "92": "uni005c",
        "93": "uni005d",
        "94": "uni005e",
        "95": "uni005f",
        "96": "uni0060",
        "97": "uni0061",
        "98": "uni0062",
        "99": "uni0063",
        "100": "uni0064",
        "101": "uni0065",
        "102": "uni0066",
        "103": "uni0067",
        "104": "uni0068",
        "105": "uni0069",
        "106": "uni006a",
        "107": "uni006b",
        "108": "uni006c",
        "109": "uni006d",
        "110": "uni006e",
        "111": "uni006f",
        "112": "uni0070",
        "113": "uni0071",
        "114": "uni0072",
        "115": "uni0073",
        "116": "uni0074",
        "117": "uni0075",
        "118": "uni0076",
        "119": "uni0077",
        "120": "uni0078",
        "121": "uni0079",
        "122": "uni007a",
        "123": "uni007b",
        "124": "uni007c",
        "125": "uni007d",
        "126": "uni007e",
        "160": "uni00a0",
        "161": "uni00a1",
        "162": "uni00a2",
        "163": "uni00a3",
        "164": "uni00a4",
        "165": "uni00a5",
        "166": "uni00a6",
        "167": "uni00a7",
        "168": "uni00a8",
        "169": "uni00a9",
        "170": "uni00aa",
        "171": "uni00ab",
        "172": "uni00ac",
        "173": "uni00ad",
        "174": "uni00ae",
        "175": "uni00af",
        "176": "uni00b0",
        "177": "uni00b1",
        "178": "uni00b2",
        "179": "uni00b3",
        "180": "uni00b4",
        "181": "uni00b5",
        "182": "uni00b6",
        "183": "uni00b7",
        "184": "uni00b8",
        "185": "uni00b9",
        "186": "uni00ba",
        "187": "uni00bb",
        "188": "uni00bc",
        "189": "uni00bd",
        "190": "uni00be",
        "191": "uni00bf",
        "192": "uni00c0",
        "193": "uni00c1",
        "194": "uni00c2",
        "195": "uni00c3",
        "196": "uni00c4",
        "197": "uni00c5",
        "198": "uni00c6",
        "199": "uni00c7",
        "200": "uni00c8",
        "201": "uni00c9",
        "202": "uni00ca",
        "203": "uni00cb",
        "204": "uni00cc",
        "205": "uni00cd",
        "206": "uni00ce",
        "207": "uni00cf",
        "208": "uni00d0",
        "209": "uni00d1",
        "210": "uni00d2",
        "211": "uni00d3",
        "212": "uni00d4",
        "213": "uni00d5",
        "214": "uni00d6",
        "215": "uni00d7",
        "216": "uni00d8",
        "217": "uni00d9",
        "218": "uni00da",
        "219": "uni00db",
        "220": "uni00dc",
        "221": "uni00dd",
        "222": "uni00de",
        "223": "uni00df",
        "224": "uni00e0",
        "225": "uni00e1",
        "226": "uni00e2",
        "227": "uni00e3",
        "228": "uni00e4",
        "229": "uni00e5",
        "230": "uni00e6",
        "231": "uni00e7",
        "232": "uni00e8",
        "233": "uni00e9",
        "234": "uni00ea",
        "235": "uni00eb",
        "236": "uni00ec",
        "237": "uni00ed",
        "238": "uni00ee",
        "239": "uni00ef",
        "240": "uni00f0",
        "241": "uni00f1",
        "242": "uni00f2",
        "243": "uni00f3",
        "244": "uni00f4",
        "245": "uni00f5",
        "246": "uni00f6",
        "247": "uni00f7",
        "248": "uni00f8",
        "249": "uni00f9",
        "250": "uni00fa",
        "251": "uni00fb",
        "252": "uni00fc",
        "253": "uni00fd",
        "254": "uni00fe",
        "255": "uni00ff",
        "256": "uni0100",
        "257": "uni0101",
        "258": "uni0102",
        "259": "uni0103",
        "260": "uni0104",
        "261": "uni0105",
        "262": "uni0106",
        "263": "uni0107",
        "264": "uni0108",
        "265": "uni0109",
        "266": "uni010a",
        "267": "uni010b",
        "268": "uni010c",
        "269": "uni010d",
        "270": "uni010e",
        "271": "uni010f",
        "272": "uni0110",
        "273": "uni0111",
        "274": "uni0112",
        "275": "uni0113",
        "276": "uni0114",
        "277": "uni0115",
        "278": "uni0116",
        "279": "uni0117",
        "280": "uni0118",
        "281": "uni0119",
        "282": "uni011a",
        "283": "uni011b",
        "284": "uni011c",
        "285": "uni011d",
        "286": "uni011e",
        "287": "uni011f",
        "288": "uni0120",
        "289": "uni0121",
        "290": "uni0122",
        "291": "uni0123",
        "292": "uni0124",
        "293": "uni0125",
        "294": "uni0126",
        "295": "uni0127",
        "296": "uni0128",
        "297": "uni0129",
        "298": "uni012a",
        "299": "uni012b",
        "300": "uni012c",
        "301": "uni012d",
        "302": "uni012e",
        "303": "uni012f",
        "304": "uni0130",
        "305": "uni0131",
        "306": "uni0132",
        "307": "uni0133",
        "308": "uni0134",
        "309": "uni0135",
        "310": "uni0136",
        "311": "uni0137",
        "312": "uni0138",
        "313": "uni0139",
        "314": "uni013a",
        "315": "uni013b",
        "316": "uni013c",
        "317": "uni013d",
        "318": "uni013e",
        "319": "uni013f",
        "320": "uni0140",
        "321": "uni0141",
        "322": "uni0142",
        "323": "uni0143",
        "324": "uni0144",
        "325": "uni0145",
        "326": "uni0146",
        "327": "uni0147",
        "328": "uni0148",
        "329": "uni0149",
        "330": "uni014a",
        "331": "uni014b",
        "332": "uni014c",
        "333": "uni014d",
        "334": "uni014e",
        "335": "uni014f",
        "336": "uni0150",
        "337": "uni0151",
        "338": "uni0152",
        "339": "uni0153",
        "340": "uni0154",
        "341": "uni0155",
        "342": "uni0156",
        "343": "uni0157",
        "344": "uni0158",
        "345": "uni0159",
        "346": "uni015a",
        "347": "uni015b",
        "348": "uni015c",
        "349": "uni015d",
        "350": "uni015e",
        "351": "uni015f",
        "352": "uni0160",
        "353": "uni0161",
        "354": "uni0162",
        "355": "uni0163",
        "356": "uni0164",
        "357": "uni0165",
        "358": "uni0166",
        "359": "uni0167",
        "360": "uni0168",
        "361": "uni0169",
        "362": "uni016a",
        "363": "uni016b",
        "364": "uni016c",
        "365": "uni016d",
        "366": "uni016e",
        "367": "uni016f",
        "368": "uni0170",
        "369": "uni0171",
        "370": "uni0172",
        "371": "uni0173",
        "372": "uni0174",
        "373": "uni0175",
        "374": "uni0176",
        "375": "uni0177",
        "376": "uni0178",
        "377": "uni0179",
        "378": "uni017a",
        "379": "uni017b",
        "380": "uni017c",
        "381": "uni017d",
        "382": "uni017e",
        "383": "uni017f",
        "399": "uni018f",
        "402": "uni0192",
        "506": "uni01fa",
        "507": "uni01fb",
        "508": "uni01fc",
        "509": "uni01fd",
        "510": "uni01fe",
        "511": "uni01ff",
        "536": "uni0218",
        "537": "uni0219",
        "538": "uni021a",
        "539": "uni021b",
        "601": "uni0259",
        "695": "uni02b7",
        "699": "uni02bb",
        "700": "uni02bc",
        "701": "uni02bd",
        "702": "uni02be",
        "703": "uni02bf",
        "710": "uni02c6",
        "711": "uni02c7",
        "713": "uni02c9",
        "728": "uni02d8",
        "729": "uni02d9",
        "730": "uni02da",
        "731": "uni02db",
        "732": "uni02dc",
        "733": "uni02dd",
        "768": "uni0300",
        "769": "uni0301",
        "770": "uni0302",
        "771": "uni0303",
        "772": "uni0304",
        "774": "uni0306",
        "775": "uni0307",
        "776": "uni0308",
        "778": "uni030a",
        "779": "uni030b",
        "780": "uni030c",
        "789": "uni0315",
        "803": "uni0323",
        "806": "uni0326",
        "807": "uni0327",
        "808": "uni0328",
        "814": "uni032e",
        "817": "uni0331",
        "956": "uni03bc",
        "4608": "uni1200",
        "4609": "uni1201",
        "4610": "uni1202",
        "4611": "uni1203",
        "4612": "uni1204",
        "4613": "uni1205",
        "4614": "uni1206",
        "4615": "uni1207",
        "4616": "uni1208",
        "4617": "uni1209",
        "4618": "uni120a",
        "4619": "uni120b",
        "4620": "uni120c",
        "4621": "uni120d",
        "4622": "uni120e",
        "4623": "uni120f",
        "4624": "uni1210",
        "4625": "uni1211",
        "4626": "uni1212",
        "4627": "uni1213",
        "4628": "uni1214",
        "4629": "uni1215",
        "4630": "uni1216",
        "4631": "uni1217",
        "4632": "uni1218",
        "4633": "uni1219",
        "4634": "uni121a",
        "4635": "uni121b",
        "4636": "uni121c",
        "4637": "uni121d",
        "4638": "uni121e",
        "4639": "uni121f",
        "4640": "uni1220",
        "4641": "uni1221",
        "4642": "uni1222",
        "4643": "uni1223",
        "4644": "uni1224",
        "4645": "uni1225",
        "4646": "uni1226",
        "4647": "uni1227",
        "4648": "uni1228",
        "4649": "uni1229",
        "4650": "uni122a",
        "4651": "uni122b",
        "4652": "uni122c",
        "4653": "uni122d",
        "4654": "uni122e",
        "4655": "uni122f",
        "4656": "uni1230",
        "4657": "uni1231",
        "4658": "uni1232",
        "4659": "uni1233",
        "4660": "uni1234",
        "4661": "uni1235",
        "4662": "uni1236",
        "4663": "uni1237",
        "4664": "uni1238",
        "4665": "uni1239",
        "4666": "uni123a",
        "4667": "uni123b",
        "4668": "uni123c",
        "4669": "uni123d",
        "4670": "uni123e",
        "4671": "uni123f",
        "4672": "uni1240",
        "4673": "uni1241",
        "4674": "uni1242",
        "4675": "uni1243",
        "4676": "uni1244",
        "4677": "uni1245",
        "4678": "uni1246",
        "4679": "uni1247",
        "4680": "uni1248",
        "4682": "uni124a",
        "4683": "uni124b",
        "4684": "uni124c",
        "4685": "uni124d",
        "4688": "uni1250",
        "4689": "uni1251",
        "4690": "uni1252",
        "4691": "uni1253",
        "4692": "uni1254",
        "4693": "uni1255",
        "4694": "uni1256",
        "4696": "uni1258",
        "4698": "uni125a",
        "4699": "uni125b",
        "4700": "uni125c",
        "4701": "uni125d",
        "4704": "uni1260",
        "4705": "uni1261",
        "4706": "uni1262",
        "4707": "uni1263",
        "4708": "uni1264",
        "4709": "uni1265",
        "4710": "uni1266",
        "4711": "uni1267",
        "4712": "uni1268",
        "4713": "uni1269",
        "4714": "uni126a",
        "4715": "uni126b",
        "4716": "uni126c",
        "4717": "uni126d",
        "4718": "uni126e",
        "4719": "uni126f",
        "4720": "uni1270",
        "4721": "uni1271",
        "4722": "uni1272",
        "4723": "uni1273",
        "4724": "uni1274",
        "4725": "uni1275",
        "4726": "uni1276",
        "4727": "uni1277",
        "4728": "uni1278",
        "4729": "uni1279",
        "4730": "uni127a",
        "4731": "uni127b",
        "4732": "uni127c",
        "4733": "uni127d",
        "4734": "uni127e",
        "4735": "uni127f",
        "4736": "uni1280",
        "4737": "uni1281",
        "4738": "uni1282",
        "4739": "uni1283",
        "4740": "uni1284",
        "4741": "uni1285",
        "4742": "uni1286",
        "4743": "uni1287",
        "4744": "uni1288",
        "4746": "uni128a",
        "4747": "uni128b",
        "4748": "uni128c",
        "4749": "uni128d",
        "4752": "uni1290",
        "4753": "uni1291",
        "4754": "uni1292",
        "4755": "uni1293",
        "4756": "uni1294",
        "4757": "uni1295",
        "4758": "uni1296",
        "4759": "uni1297",
        "4760": "uni1298",
        "4761": "uni1299",
        "4762": "uni129a",
        "4763": "uni129b",
        "4764": "uni129c",
        "4765": "uni129d",
        "4766": "uni129e",
        "4767": "uni129f",
        "4768": "uni12a0",
        "4769": "uni12a1",
        "4770": "uni12a2",
        "4771": "uni12a3",
        "4772": "uni12a4",
        "4773": "uni12a5",
        "4774": "uni12a6",
        "4775": "uni12a7",
        "4776": "uni12a8",
        "4777": "uni12a9",
        "4778": "uni12aa",
        "4779": "uni12ab",
        "4780": "uni12ac",
        "4781": "uni12ad",
        "4782": "uni12ae",
        "4783": "uni12af",
        "4784": "uni12b0",
        "4786": "uni12b2",
        "4787": "uni12b3",
        "4788": "uni12b4",
        "4789": "uni12b5",
        "4792": "uni12b8",
        "4793": "uni12b9",
        "4794": "uni12ba",
        "4795": "uni12bb",
        "4796": "uni12bc",
        "4797": "uni12bd",
        "4798": "uni12be",
        "4800": "uni12c0",
        "4802": "uni12c2",
        "4803": "uni12c3",
        "4804": "uni12c4",
        "4805": "uni12c5",
        "4808": "uni12c8",
        "4809": "uni12c9",
        "4810": "uni12ca",
        "4811": "uni12cb",
        "4812": "uni12cc",
        "4813": "uni12cd",
        "4814": "uni12ce",
        "4815": "uni12cf",
        "4816": "uni12d0",
        "4817": "uni12d1",
        "4818": "uni12d2",
        "4819": "uni12d3",
        "4820": "uni12d4",
        "4821": "uni12d5",
        "4822": "uni12d6",
        "4824": "uni12d8",
        "4825": "uni12d9",
        "4826": "uni12da",
        "4827": "uni12db",
        "4828": "uni12dc",
        "4829": "uni12dd",
        "4830": "uni12de",
        "4831": "uni12df",
        "4832": "uni12e0",
        "4833": "uni12e1",
        "4834": "uni12e2",
        "4835": "uni12e3",
        "4836": "uni12e4",
        "4837": "uni12e5",
        "4838": "uni12e6",
        "4839": "uni12e7",
        "4840": "uni12e8",
        "4841": "uni12e9",
        "4842": "uni12ea",
        "4843": "uni12eb",
        "4844": "uni12ec",
        "4845": "uni12ed",
        "4846": "uni12ee",
        "4847": "uni12ef",
        "4848": "uni12f0",
        "4849": "uni12f1",
        "4850": "uni12f2",
        "4851": "uni12f3",
        "4852": "uni12f4",
        "4853": "uni12f5",
        "4854": "uni12f6",
        "4855": "uni12f7",
        "4856": "uni12f8",
        "4857": "uni12f9",
        "4858": "uni12fa",
        "4859": "uni12fb",
        "4860": "uni12fc",
        "4861": "uni12fd",
        "4862": "uni12fe",
        "4863": "uni12ff",
        "4864": "uni1300",
        "4865": "uni1301",
        "4866": "uni1302",
        "4867": "uni1303",
        "4868": "uni1304",
        "4869": "uni1305",
        "4870": "uni1306",
        "4871": "uni1307",
        "4872": "uni1308",
        "4873": "uni1309",
        "4874": "uni130a",
        "4875": "uni130b",
        "4876": "uni130c",
        "4877": "uni130d",
        "4878": "uni130e",
        "4879": "uni130f",
        "4880": "uni1310",
        "4882": "uni1312",
        "4883": "uni1313",
        "4884": "uni1314",
        "4885": "uni1315",
        "4888": "uni1318",
        "4889": "uni1319",
        "4890": "uni131a",
        "4891": "uni131b",
        "4892": "uni131c",
        "4893": "uni131d",
        "4894": "uni131e",
        "4895": "uni131f",
        "4896": "uni1320",
        "4897": "uni1321",
        "4898": "uni1322",
        "4899": "uni1323",
        "4900": "uni1324",
        "4901": "uni1325",
        "4902": "uni1326",
        "4903": "uni1327",
        "4904": "uni1328",
        "4905": "uni1329",
        "4906": "uni132a",
        "4907": "uni132b",
        "4908": "uni132c",
        "4909": "uni132d",
        "4910": "uni132e",
        "4911": "uni132f",
        "4912": "uni1330",
        "4913": "uni1331",
        "4914": "uni1332",
        "4915": "uni1333",
        "4916": "uni1334",
        "4917": "uni1335",
        "4918": "uni1336",
        "4919": "uni1337",
        "4920": "uni1338",
        "4921": "uni1339",
        "4922": "uni133a",
        "4923": "uni133b",
        "4924": "uni133c",
        "4925": "uni133d",
        "4926": "uni133e",
        "4927": "uni133f",
        "4928": "uni1340",
        "4929": "uni1341",
        "4930": "uni1342",
        "4931": "uni1343",
        "4932": "uni1344",
        "4933": "uni1345",
        "4934": "uni1346",
        "4935": "uni1347",
        "4936": "uni1348",
        "4937": "uni1349",
        "4938": "uni134a",
        "4939": "uni134b",
        "4940": "uni134c",
        "4941": "uni134d",
        "4942": "uni134e",
        "4943": "uni134f",
        "4944": "uni1350",
        "4945": "uni1351",
        "4946": "uni1352",
        "4947": "uni1353",
        "4948": "uni1354",
        "4949": "uni1355",
        "4950": "uni1356",
        "4951": "uni1357",
        "4952": "uni1358",
        "4953": "uni1359",
        "4954": "uni135a",
        "4957": "uni135d",
        "4958": "uni135e",
        "4959": "uni135f",
        "4960": "uni1360",
        "4961": "uni1361",
        "4962": "uni1362",
        "4963": "uni1363",
        "4964": "uni1364",
        "4965": "uni1365",
        "4966": "uni1366",
        "4967": "uni1367",
        "4968": "uni1368",
        "4969": "uni1369",
        "4970": "uni136a",
        "4971": "uni136b",
        "4972": "uni136c",
        "4973": "uni136d",
        "4974": "uni136e",
        "4975": "uni136f",
        "4976": "uni1370",
        "4977": "uni1371",
        "4978": "uni1372",
        "4979": "uni1373",
        "4980": "uni1374",
        "4981": "uni1375",
        "4982": "uni1376",
        "4983": "uni1377",
        "4984": "uni1378",
        "4985": "uni1379",
        "4986": "uni137a",
        "4987": "uni137b",
        "4988": "uni137c",
        "4992": "uni1380",
        "4993": "uni1381",
        "4994": "uni1382",
        "4995": "uni1383",
        "4996": "uni1384",
        "4997": "uni1385",
        "4998": "uni1386",
        "4999": "uni1387",
        "5000": "uni1388",
        "5001": "uni1389",
        "5002": "uni138a",
        "5003": "uni138b",
        "5004": "uni138c",
        "5005": "uni138d",
        "5006": "uni138e",
        "5007": "uni138f",
        "5008": "uni1390",
        "5009": "uni1391",
        "5010": "uni1392",
        "5011": "uni1393",
        "5012": "uni1394",
        "5013": "uni1395",
        "5014": "uni1396",
        "5015": "uni1397",
        "5016": "uni1398",
        "5017": "uni1399",
        "7692": "uni1e0c",
        "7693": "uni1e0d",
        "7716": "uni1e24",
        "7717": "uni1e25",
        "7722": "uni1e2a",
        "7723": "uni1e2b",
        "7728": "uni1e30",
        "7729": "uni1e31",
        "7732": "uni1e34",
        "7733": "uni1e35",
        "7766": "uni1e56",
        "7767": "uni1e57",
        "7776": "uni1e60",
        "7777": "uni1e61",
        "7778": "uni1e62",
        "7779": "uni1e63",
        "7788": "uni1e6c",
        "7789": "uni1e6d",
        "7808": "uni1e80",
        "7809": "uni1e81",
        "7810": "uni1e82",
        "7811": "uni1e83",
        "7812": "uni1e84",
        "7813": "uni1e85",
        "7826": "uni1e92",
        "7827": "uni1e93",
        "7922": "uni1ef2",
        "7923": "uni1ef3",
        "8211": "uni2013",
        "8212": "uni2014",
        "8216": "uni2018",
        "8217": "uni2019",
        "8218": "uni201a",
        "8220": "uni201c",
        "8221": "uni201d",
        "8222": "uni201e",
        "8224": "uni2020",
        "8225": "uni2021",
        "8226": "uni2022",
        "8230": "uni2026",
        "8240": "uni2030",
        "8249": "uni2039",
        "8250": "uni203a",
        "8260": "uni2044",
        "8308": "uni2074",
        "8364": "uni20ac",
        "8482": "uni2122",
        "8722": "uni2212",
        "8725": "uni2215",
        "8729": "uni2219",
        "11648": "uni2d80",
        "11649": "uni2d81",
        "11650": "uni2d82",
        "11651": "uni2d83",
        "11652": "uni2d84",
        "11653": "uni2d85",
        "11654": "uni2d86",
        "11655": "uni2d87",
        "11656": "uni2d88",
        "11657": "uni2d89",
        "11658": "uni2d8a",
        "11659": "uni2d8b",
        "11660": "uni2d8c",
        "11661": "uni2d8d",
        "11662": "uni2d8e",
        "11663": "uni2d8f",
        "11664": "uni2d90",
        "11665": "uni2d91",
        "11666": "uni2d92",
        "11667": "uni2d93",
        "11668": "uni2d94",
        "11669": "uni2d95",
        "11670": "uni2d96",
        "11680": "uni2da0",
        "11681": "uni2da1",
        "11682": "uni2da2",
        "11683": "uni2da3",
        "11684": "uni2da4",
        "11685": "uni2da5",
        "11686": "uni2da6",
        "11688": "uni2da8",
        "11689": "uni2da9",
        "11690": "uni2daa",
        "11691": "uni2dab",
        "11692": "uni2dac",
        "11693": "uni2dad",
        "11694": "uni2dae",
        "11696": "uni2db0",
        "11697": "uni2db1",
        "11698": "uni2db2",
        "11699": "uni2db3",
        "11700": "uni2db4",
        "11701": "uni2db5",
        "11702": "uni2db6",
        "11704": "uni2db8",
        "11705": "uni2db9",
        "11706": "uni2dba",
        "11707": "uni2dbb",
        "11708": "uni2dbc",
        "11709": "uni2dbd",
        "11710": "uni2dbe",
        "11712": "uni2dc0",
        "11713": "uni2dc1",
        "11714": "uni2dc2",
        "11715": "uni2dc3",
        "11716": "uni2dc4",
        "11717": "uni2dc5",
        "11718": "uni2dc6",
        "11720": "uni2dc8",
        "11721": "uni2dc9",
        "11722": "uni2dca",
        "11723": "uni2dcb",
        "11724": "uni2dcc",
        "11725": "uni2dcd",
        "11726": "uni2dce",
        "11728": "uni2dd0",
        "11729": "uni2dd1",
        "11730": "uni2dd2",
        "11731": "uni2dd3",
        "11732": "uni2dd4",
        "11733": "uni2dd5",
        "11734": "uni2dd6",
        "11736": "uni2dd8",
        "11737": "uni2dd9",
        "11738": "uni2dda",
        "11739": "uni2ddb",
        "11740": "uni2ddc",
        "11741": "uni2ddd",
        "11742": "uni2dde",
        "43777": "uniab01",
        "43778": "uniab02",
        "43779": "uniab03",
        "43780": "uniab04",
        "43781": "uniab05",
        "43782": "uniab06",
        "43785": "uniab09",
        "43786": "uniab0a",
        "43787": "uniab0b",
        "43788": "uniab0c",
        "43789": "uniab0d",
        "43790": "uniab0e",
        "43793": "uniab11",
        "43794": "uniab12",
        "43795": "uniab13",
        "43796": "uniab14",
        "43797": "uniab15",
        "43798": "uniab16",
        "43808": "uniab20",
        "43809": "uniab21",
        "43810": "uniab22",
        "43811": "uniab23",
        "43812": "uniab24",
        "43813": "uniab25",
        "43814": "uniab26",
        "43816": "uniab28",
        "43817": "uniab29",
        "43818": "uniab2a",
        "43819": "uniab2b",
        "43820": "uniab2c",
        "43821": "uniab2d",
        "43822": "uniab2e",
        "64256": "unifb00",
        "64257": "unifb01",
        "64258": "unifb02",
        "64259": "unifb03",
        "64260": "unifb04"
    },
    "isUnicode": true,
    "EncodingScheme": "FontSpecific",
    "FontName": "Nyala",
    "FullName": "Nyala",
    "Version": "Version 5.01",
    "PostScriptName": "Nyala-Regular",
    "Weight": "Medium",
    "ItalicAngle": "0",
    "IsFixedPitch": "false",
    "UnderlineThickness": "24",
    "UnderlinePosition": "-85",
    "FontHeightOffset": "125",
    "Ascender": "750",
    "Descender": "-170",
    "FontBBox": [
        "-470",
        "-261",
        "1279",
        "893"
    ],
    "StartCharMetrics": "1062",
    "C": {
        "32": 293,
        "33": 229,
        "34": 303,
        "35": 394,
        "36": 431,
        "37": 710,
        "38": 585,
        "39": 167,
        "40": 325,
        "41": 325,
        "42": 377,
        "43": 393,
        "44": 185,
        "45": 295,
        "46": 185,
        "47": 260,
        "48": 472,
        "49": 244,
        "50": 441,
        "51": 454,
        "52": 495,
        "53": 464,
        "54": 506,
        "55": 451,
        "56": 493,
        "57": 499,
        "58": 185,
        "59": 185,
        "60": 393,
        "61": 393,
        "62": 393,
        "63": 367,
        "64": 739,
        "65": 556,
        "66": 495,
        "67": 577,
        "68": 626,
        "69": 476,
        "70": 432,
        "71": 614,
        "72": 623,
        "73": 247,
        "74": 227,
        "75": 538,
        "76": 449,
        "77": 750,
        "78": 596,
        "79": 659,
        "80": 470,
        "81": 659,
        "82": 526,
        "83": 451,
        "84": 533,
        "85": 598,
        "86": 561,
        "87": 814,
        "88": 482,
        "89": 481,
        "90": 502,
        "91": 314,
        "92": 260,
        "93": 314,
        "94": 393,
        "95": 293,
        "96": 244,
        "97": 396,
        "98": 473,
        "99": 384,
        "100": 467,
        "101": 391,
        "102": 269,
        "103": 437,
        "104": 471,
        "105": 224,
        "106": 224,
        "107": 423,
        "108": 216,
        "109": 723,
        "110": 478,
        "111": 444,
        "112": 480,
        "113": 466,
        "114": 345,
        "115": 345,
        "116": 300,
        "117": 480,
        "118": 402,
        "119": 629,
        "120": 385,
        "121": 399,
        "122": 399,
        "123": 314,
        "124": 92,
        "125": 304,
        "126": 393,
        "160": 293,
        "161": 229,
        "162": 389,
        "163": 460,
        "164": 455,
        "165": 468,
        "166": 258,
        "167": 455,
        "168": 244,
        "169": 703,
        "170": 315,
        "171": 348,
        "172": 393,
        "173": 295,
        "174": 415,
        "175": 244,
        "176": 278,
        "177": 393,
        "178": 324,
        "179": 310,
        "180": 244,
        "181": 462,
        "182": 503,
        "183": 205,
        "184": 244,
        "185": 197,
        "186": 355,
        "187": 348,
        "188": 557,
        "189": 622,
        "190": 669,
        "191": 362,
        "192": 571,
        "193": 571,
        "194": 571,
        "195": 571,
        "196": 571,
        "197": 571,
        "198": 747,
        "199": 577,
        "200": 476,
        "201": 476,
        "202": 476,
        "203": 476,
        "204": 247,
        "205": 247,
        "206": 247,
        "207": 247,
        "208": 632,
        "209": 596,
        "210": 659,
        "211": 659,
        "212": 659,
        "213": 659,
        "214": 659,
        "215": 393,
        "216": 659,
        "217": 598,
        "218": 598,
        "219": 598,
        "220": 598,
        "221": 481,
        "222": 490,
        "223": 518,
        "224": 396,
        "225": 396,
        "226": 396,
        "227": 396,
        "228": 396,
        "229": 396,
        "230": 610,
        "231": 384,
        "232": 391,
        "233": 391,
        "234": 391,
        "235": 391,
        "236": 224,
        "237": 224,
        "238": 224,
        "239": 224,
        "240": 458,
        "241": 478,
        "242": 444,
        "243": 444,
        "244": 444,
        "245": 444,
        "246": 444,
        "247": 393,
        "248": 444,
        "249": 480,
        "250": 480,
        "251": 480,
        "252": 480,
        "253": 399,
        "254": 480,
        "255": 399,
        "256": 571,
        "257": 396,
        "258": 571,
        "259": 396,
        "260": 571,
        "261": 396,
        "262": 577,
        "263": 384,
        "264": 577,
        "265": 384,
        "266": 577,
        "267": 384,
        "268": 577,
        "269": 384,
        "270": 626,
        "271": 571,
        "272": 632,
        "273": 467,
        "274": 476,
        "275": 391,
        "276": 476,
        "277": 391,
        "278": 476,
        "279": 391,
        "280": 476,
        "281": 391,
        "282": 476,
        "283": 391,
        "284": 614,
        "285": 437,
        "286": 614,
        "287": 437,
        "288": 614,
        "289": 437,
        "290": 614,
        "291": 437,
        "292": 623,
        "293": 471,
        "294": 623,
        "295": 471,
        "296": 247,
        "297": 224,
        "298": 247,
        "299": 224,
        "300": 247,
        "301": 224,
        "302": 247,
        "303": 224,
        "304": 247,
        "305": 224,
        "306": 474,
        "307": 447,
        "308": 227,
        "309": 224,
        "310": 538,
        "311": 423,
        "312": 430,
        "313": 449,
        "314": 216,
        "315": 449,
        "316": 216,
        "317": 449,
        "318": 320,
        "319": 459,
        "320": 304,
        "321": 452,
        "322": 233,
        "323": 596,
        "324": 478,
        "325": 596,
        "326": 478,
        "327": 596,
        "328": 478,
        "329": 537,
        "330": 598,
        "331": 478,
        "332": 659,
        "333": 444,
        "334": 659,
        "335": 444,
        "336": 659,
        "337": 444,
        "338": 884,
        "339": 677,
        "340": 526,
        "341": 354,
        "342": 526,
        "343": 354,
        "344": 526,
        "345": 354,
        "346": 451,
        "347": 347,
        "348": 451,
        "349": 347,
        "350": 451,
        "351": 347,
        "352": 451,
        "353": 347,
        "354": 533,
        "355": 300,
        "356": 533,
        "357": 324,
        "358": 533,
        "359": 300,
        "360": 598,
        "361": 480,
        "362": 598,
        "363": 480,
        "364": 598,
        "365": 480,
        "366": 598,
        "367": 480,
        "368": 598,
        "369": 480,
        "370": 598,
        "371": 480,
        "372": 814,
        "373": 629,
        "374": 481,
        "375": 399,
        "376": 481,
        "377": 517,
        "378": 397,
        "379": 517,
        "380": 397,
        "381": 517,
        "382": 397,
        "383": 260,
        "399": 650,
        "402": 469,
        "506": 571,
        "507": 396,
        "508": 747,
        "509": 610,
        "510": 659,
        "511": 444,
        "536": 451,
        "537": 347,
        "538": 533,
        "539": 300,
        "601": 391,
        "695": 418,
        "699": 181,
        "700": 186,
        "701": 186,
        "702": 197,
        "703": 197,
        "710": 244,
        "711": 244,
        "713": 244,
        "728": 244,
        "729": 244,
        "730": 244,
        "731": 244,
        "732": 244,
        "733": 244,
        "768": 0,
        "769": 0,
        "770": 0,
        "771": 0,
        "772": 0,
        "774": 0,
        "775": 0,
        "776": 0,
        "778": 0,
        "779": 0,
        "780": 0,
        "789": 104,
        "803": 0,
        "806": 0,
        "807": 0,
        "808": 0,
        "814": 0,
        "817": 0,
        "956": 462,
        "4608": 508,
        "4609": 707,
        "4610": 526,
        "4611": 469,
        "4612": 529,
        "4613": 521,
        "4614": 676,
        "4615": 823,
        "4616": 512,
        "4617": 668,
        "4618": 718,
        "4619": 493,
        "4620": 668,
        "4621": 608,
        "4622": 749,
        "4623": 635,
        "4624": 708,
        "4625": 871,
        "4626": 904,
        "4627": 684,
        "4628": 851,
        "4629": 708,
        "4630": 692,
        "4631": 867,
        "4632": 812,
        "4633": 1031,
        "4634": 915,
        "4635": 782,
        "4636": 875,
        "4637": 753,
        "4638": 762,
        "4639": 890,
        "4640": 674,
        "4641": 877,
        "4642": 782,
        "4643": 644,
        "4644": 745,
        "4645": 862,
        "4646": 655,
        "4647": 772,
        "4648": 511,
        "4649": 589,
        "4650": 508,
        "4651": 638,
        "4652": 614,
        "4653": 511,
        "4654": 600,
        "4655": 680,
        "4656": 505,
        "4657": 668,
        "4658": 689,
        "4659": 490,
        "4660": 657,
        "4661": 501,
        "4662": 495,
        "4663": 631,
        "4664": 519,
        "4665": 676,
        "4666": 690,
        "4667": 519,
        "4668": 655,
        "4669": 542,
        "4670": 538,
        "4671": 656,
        "4672": 563,
        "4673": 572,
        "4674": 570,
        "4675": 684,
        "4676": 572,
        "4677": 563,
        "4678": 548,
        "4679": 553,
        "4680": 615,
        "4682": 906,
        "4683": 573,
        "4684": 569,
        "4685": 876,
        "4688": 563,
        "4689": 572,
        "4690": 570,
        "4691": 672,
        "4692": 568,
        "4693": 567,
        "4694": 550,
        "4696": 624,
        "4698": 905,
        "4699": 571,
        "4700": 574,
        "4701": 869,
        "4704": 511,
        "4705": 702,
        "4706": 702,
        "4707": 507,
        "4708": 666,
        "4709": 677,
        "4710": 500,
        "4711": 666,
        "4712": 529,
        "4713": 707,
        "4714": 713,
        "4715": 529,
        "4716": 679,
        "4717": 681,
        "4718": 529,
        "4719": 684,
        "4720": 609,
        "4721": 609,
        "4722": 609,
        "4723": 701,
        "4724": 609,
        "4725": 609,
        "4726": 607,
        "4727": 623,
        "4728": 616,
        "4729": 616,
        "4730": 616,
        "4731": 667,
        "4732": 616,
        "4733": 613,
        "4734": 607,
        "4735": 646,
        "4736": 528,
        "4737": 710,
        "4738": 625,
        "4739": 540,
        "4740": 661,
        "4741": 515,
        "4742": 790,
        "4743": 790,
        "4744": 817,
        "4746": 843,
        "4747": 626,
        "4748": 676,
        "4749": 783,
        "4752": 348,
        "4753": 513,
        "4754": 449,
        "4755": 489,
        "4756": 436,
        "4757": 471,
        "4758": 586,
        "4759": 521,
        "4760": 582,
        "4761": 705,
        "4762": 621,
        "4763": 572,
        "4764": 604,
        "4765": 549,
        "4766": 644,
        "4767": 572,
        "4768": 503,
        "4769": 668,
        "4770": 708,
        "4771": 474,
        "4772": 644,
        "4773": 505,
        "4774": 488,
        "4775": 610,
        "4776": 534,
        "4777": 704,
        "4778": 720,
        "4779": 534,
        "4780": 698,
        "4781": 535,
        "4782": 536,
        "4783": 673,
        "4784": 817,
        "4786": 822,
        "4787": 668,
        "4788": 677,
        "4789": 639,
        "4792": 673,
        "4793": 851,
        "4794": 863,
        "4795": 673,
        "4796": 826,
        "4797": 696,
        "4798": 675,
        "4800": 959,
        "4802": 974,
        "4803": 757,
        "4804": 827,
        "4805": 827,
        "4808": 664,
        "4809": 822,
        "4810": 583,
        "4811": 579,
        "4812": 579,
        "4813": 872,
        "4814": 610,
        "4815": 774,
        "4816": 491,
        "4817": 707,
        "4818": 669,
        "4819": 537,
        "4820": 658,
        "4821": 455,
        "4822": 490,
        "4824": 466,
        "4825": 665,
        "4826": 638,
        "4827": 453,
        "4828": 587,
        "4829": 601,
        "4830": 464,
        "4831": 603,
        "4832": 814,
        "4833": 841,
        "4834": 832,
        "4835": 814,
        "4836": 819,
        "4837": 811,
        "4838": 813,
        "4839": 824,
        "4840": 391,
        "4841": 479,
        "4842": 595,
        "4843": 481,
        "4844": 573,
        "4845": 622,
        "4846": 588,
        "4847": 724,
        "4848": 562,
        "4849": 720,
        "4850": 683,
        "4851": 568,
        "4852": 747,
        "4853": 676,
        "4854": 633,
        "4855": 774,
        "4856": 580,
        "4857": 718,
        "4858": 683,
        "4859": 569,
        "4860": 749,
        "4861": 677,
        "4862": 631,
        "4863": 790,
        "4864": 598,
        "4865": 709,
        "4866": 657,
        "4867": 584,
        "4868": 667,
        "4869": 679,
        "4870": 641,
        "4871": 790,
        "4872": 379,
        "4873": 569,
        "4874": 531,
        "4875": 551,
        "4876": 494,
        "4877": 565,
        "4878": 410,
        "4879": 453,
        "4880": 731,
        "4882": 717,
        "4883": 494,
        "4884": 576,
        "4885": 670,
        "4888": 450,
        "4889": 616,
        "4890": 579,
        "4891": 556,
        "4892": 546,
        "4893": 568,
        "4894": 447,
        "4895": 531,
        "4896": 763,
        "4897": 936,
        "4898": 945,
        "4899": 762,
        "4900": 911,
        "4901": 645,
        "4902": 712,
        "4903": 901,
        "4904": 1016,
        "4905": 1033,
        "4906": 1018,
        "4907": 929,
        "4908": 1145,
        "4909": 922,
        "4910": 992,
        "4911": 1056,
        "4912": 503,
        "4913": 682,
        "4914": 707,
        "4915": 497,
        "4916": 654,
        "4917": 608,
        "4918": 469,
        "4919": 677,
        "4920": 503,
        "4921": 682,
        "4922": 707,
        "4923": 497,
        "4924": 654,
        "4925": 608,
        "4926": 469,
        "4927": 677,
        "4928": 453,
        "4929": 667,
        "4930": 519,
        "4931": 386,
        "4932": 481,
        "4933": 441,
        "4934": 491,
        "4935": 561,
        "4936": 583,
        "4937": 635,
        "4938": 574,
        "4939": 631,
        "4940": 674,
        "4941": 609,
        "4942": 644,
        "4943": 631,
        "4944": 639,
        "4945": 639,
        "4946": 639,
        "4947": 741,
        "4948": 639,
        "4949": 639,
        "4950": 742,
        "4951": 643,
        "4952": 622,
        "4953": 782,
        "4954": 621,
        "4957": 0,
        "4958": 0,
        "4959": 0,
        "4960": 704,
        "4961": 336,
        "4962": 502,
        "4963": 368,
        "4964": 368,
        "4965": 393,
        "4966": 640,
        "4967": 340,
        "4968": 720,
        "4969": 467,
        "4970": 460,
        "4971": 476,
        "4972": 470,
        "4973": 507,
        "4974": 466,
        "4975": 490,
        "4976": 601,
        "4977": 510,
        "4978": 469,
        "4979": 612,
        "4980": 646,
        "4981": 608,
        "4982": 460,
        "4983": 630,
        "4984": 600,
        "4985": 791,
        "4986": 464,
        "4987": 458,
        "4988": 692,
        "4992": 1109,
        "4993": 1088,
        "4994": 875,
        "4995": 1053,
        "4996": 792,
        "4997": 811,
        "4998": 666,
        "4999": 958,
        "5000": 692,
        "5001": 705,
        "5002": 685,
        "5003": 698,
        "5004": 682,
        "5005": 723,
        "5006": 639,
        "5007": 727,
        "5008": 364,
        "5009": 437,
        "5010": 340,
        "5011": 340,
        "5012": 437,
        "5013": 798,
        "5014": 407,
        "5015": 922,
        "5016": 922,
        "5017": 400,
        "7692": 626,
        "7693": 467,
        "7716": 623,
        "7717": 471,
        "7722": 623,
        "7723": 471,
        "7728": 538,
        "7729": 423,
        "7732": 538,
        "7733": 423,
        "7766": 470,
        "7767": 480,
        "7776": 451,
        "7777": 347,
        "7778": 451,
        "7779": 347,
        "7788": 533,
        "7789": 300,
        "7808": 814,
        "7809": 629,
        "7810": 814,
        "7811": 629,
        "7812": 814,
        "7813": 629,
        "7826": 517,
        "7827": 397,
        "7922": 481,
        "7923": 399,
        "8211": 500,
        "8212": 1000,
        "8216": 186,
        "8217": 186,
        "8218": 186,
        "8220": 313,
        "8221": 313,
        "8222": 313,
        "8224": 457,
        "8225": 457,
        "8226": 383,
        "8230": 518,
        "8240": 1032,
        "8249": 204,
        "8250": 204,
        "8260": 98,
        "8308": 306,
        "8364": 495,
        "8482": 679,
        "8722": 393,
        "8725": 98,
        "8729": 205,
        "11648": 887,
        "11649": 766,
        "11650": 754,
        "11651": 658,
        "11652": 681,
        "11653": 662,
        "11654": 609,
        "11655": 609,
        "11656": 589,
        "11657": 646,
        "11658": 588,
        "11659": 603,
        "11660": 730,
        "11661": 730,
        "11662": 689,
        "11663": 876,
        "11664": 1139,
        "11665": 553,
        "11666": 753,
        "11667": 702,
        "11668": 739,
        "11669": 549,
        "11670": 690,
        "11680": 665,
        "11681": 823,
        "11682": 836,
        "11683": 671,
        "11684": 802,
        "11685": 655,
        "11686": 685,
        "11688": 619,
        "11689": 619,
        "11690": 619,
        "11691": 669,
        "11692": 619,
        "11693": 616,
        "11694": 609,
        "11696": 818,
        "11697": 845,
        "11698": 835,
        "11699": 818,
        "11700": 822,
        "11701": 813,
        "11702": 816,
        "11704": 1171,
        "11705": 1188,
        "11706": 1172,
        "11707": 1112,
        "11708": 1299,
        "11709": 1107,
        "11710": 1158,
        "11712": 563,
        "11713": 572,
        "11714": 570,
        "11715": 684,
        "11716": 572,
        "11717": 563,
        "11718": 548,
        "11720": 534,
        "11721": 704,
        "11722": 720,
        "11723": 534,
        "11724": 698,
        "11725": 535,
        "11726": 536,
        "11728": 673,
        "11729": 851,
        "11730": 863,
        "11731": 673,
        "11732": 826,
        "11733": 696,
        "11734": 675,
        "11736": 379,
        "11737": 569,
        "11738": 531,
        "11739": 551,
        "11740": 494,
        "11741": 565,
        "11742": 410,
        "43777": 685,
        "43778": 689,
        "43779": 490,
        "43780": 657,
        "43781": 501,
        "43782": 495,
        "43785": 718,
        "43786": 683,
        "43787": 569,
        "43788": 749,
        "43789": 677,
        "43790": 631,
        "43793": 665,
        "43794": 638,
        "43795": 453,
        "43796": 587,
        "43797": 601,
        "43798": 464,
        "43808": 1016,
        "43809": 1033,
        "43810": 1018,
        "43811": 929,
        "43812": 1145,
        "43813": 922,
        "43814": 992,
        "43816": 503,
        "43817": 682,
        "43818": 707,
        "43819": 497,
        "43820": 654,
        "43821": 608,
        "43822": 469,
        "64256": 518,
        "64257": 463,
        "64258": 468,
        "64259": 712,
        "64260": 717
    },
    "CIDtoGID_Compressed": true,
    "CIDtoGID": "eJzt23XUFeUWx\/Hf3nuQ7u7u7u7uBsHu7m69dncAKl3S3SUoWNiJYieKgqQg3OMry3XvguvSRXn1+1lrnmf2k3vOzPnrzJH2U\/iO6BrV4sjo5BuiSxSKwlEuWvom3+5bI0dUjxpRM2pF7agTdaNe1I8GvsU3R\/toFx18l2+0QTbYhtjj9oQ9aUNtmA23ETbSRtloG2NjbZyNt6dsgk20STbZpthUm2bTo1j0iOLRM\/rESV7da3hNr+W1vY7X9Xpe3xt4Q2\/kjb2JN\/Vm3txbeEtv5a29jbf1dt7eO0SpyBmlo9f+Xnza9e+MATEwjomjondUjHOjcvSNLNHRt0eVOD+6RetoFI3jlOgelaJAXBkNo19kjabRLJr7bpthM22WzbY5Nt8W2Qp73l6wF221fWQf2yf2mVe1LbbNtttPtsN2RhuX5\/V8nt8Lehmv5uO9o3fyzt7Fu3oP7+0D\/Xg\/wU\/0k\/1Sv8wv9yt9pd\/t9\/n9\/oA\/6A9FW3\/Mp\/hUn+YzfLGv8qU217vZPO9uC72XLfG+ttT72XIfYMu8v630Y+w5P85e9lPsFT\/VXvXT7DU\/3V7yk+xNP8ve9nPsHT\/X3vXzbI1fYB\/6JfapX2Gf+1X2hV9tX\/k19qVfZ9\/49bbOb7Dv\/Ea\/2b73W2yD32Y\/+K32o99hG\/122+R32la\/xzb7XX6vV\/Fn7Wd\/2Hb5I7bbH3X3wZ7eh3pGH+4ZfJhn8hGe2Ud6Nh\/jWXyU5\/KJntMneB6f7AV8uhfymV7YZ3kRn+1FfY4X87le0hd4WV\/i5by8L\/OKvtwr+NP+1O\/fXK+cdouPPgDPyV+ILfCettj7uPmgPzvXs\/vYXz7vg5HXH8zgmcO39\/6KE\/fUx8ZxYXFCHP9fvafFGany\/N9d4cK4PC6O6+PsuPSAZHRynBqnxzlxQer8orgizkvVl8RlceZeI8\/6nVX+lVZeHVfFDf\/Rel1aee2ByPPvJrof7gwAAAAAAAAAAAAA\/O0kSqcjlF4ZlFGZ4j5lVhZlVTZlVw7lVC7lVh7lVT7lVwEVVCEVVhEVVTEVVwmVVCmVVhmVVTmVVwVVVCVVVhVVVTVVVw3VVC3VVh3VVT3VVwM1VCM1VhM1VTM1Vwu1VCu1Vhu1VTu1Vwd1jPvVKZVTZ3VRV3VLy6+7eqineqm3+qhvKu6XOvrrSA3QwLT+o3S0jtGxOk7H6wSdqJN0sk7RqTpNp+sMnamzdLbO0bk6T+frAl2oi3SxLtGlukyX6wpdqat0ta7RtbpO1+uGeEC\/\/JJ9o27Szbolbf1bdZtu1x26U3fpbt2je3Wf7tcDelAP6WE9okf1mAZpsIbocT2hJzVUwzRcIzRSozQ6HtSY1BpjNU7j9eu7JhM0UZM0WVM0VdNS8fTUMUMzNUuz0\/rnaK7mab4WaKEWxUNarCVaqmV6Wsu1ItX\/jJ7VSq3Sc3peL+hFvaTVelmv6FW9ptf1ht7UW3pb7+hdvac18bDe1wdaqw\/1kT7WJ\/pUn+lzfaEv9ZW+1jdap2\/1ndbre\/2gDdqoH7VJm7VFW7VN2\/VTPKIdqT136mft0u5f0jOZmVtYYunsiHjU0lsGy2iZLLNlsayWzbJbDstpuSy35bG8ls\/yWwEraIWssBWxolbMilsJK2mlrLSVsbJWzspbBatolayyVbGq8ZhVs+pWw2paLattdayu1bP61sAaWiNrbE2sqTWz5tYi7cFNknSxLbZbS2tlra2NtbV21t46WEfrZJ2ti3W1btbdelhP62W9rY\/1tX7W3460ATbQjrI97\/TEoBgcQ+LxeCKejKExLIbHiBgZo2J0jImxMS5+ih2xM36OXbE7UWKJJ3Gwv5IAAAAAAAAAcDDZKj\/2T41f6xf\/dv6BX\/Tb+bee9t8wW+837W9OHj5kr7asPtpz+Li92nP7pD+0ZnGf5yV8vpfyhf9zTCVf8ecy\/Wvx0r7ocOeA\/2eRO\/LuOfOIOCJVJ5Eu0qfq8lEh8v\/a59v2MbPzXi0ZIuM+xrU4gOnuQzQ5uOvvtV\/\/Q7vf4RRVD3cGOJiiVVrZYk9U4DCmAgAAAAAAAADAHxLj46mYEBNjUkyOKTE1psX0mBEzY1bMjjkxN+bF\/FgQC2NRLI4l+5i\/NJbF07E8VsQz8WwqXhmr4rl4Pl6IF+OlVLw6Xo5X4tV4LV6PN1Lxm\/FWvB3vxLvxXqxJxe\/HB7E2PoyP4uP4JBV\/Gp\/F5\/FFfBlfxdep+JtYF9\/Gd7E+vo8fUvGG2Bg\/xqbYHFti66H+tAAAAAAAAAAAAAAAAAAAAAAAAAAAAAAAAAAAAAAAAAAAAAAAAAAAAAAAAAAAAAAAAAAAAAAAAAAAAAAAAAAAAAAAAAAAAAAAAAAAAAAAAAAAAAAAAAAAAAAAAAAAwD9DckSSPsmQZEwyJZnT4ixJ1iRbkj3JkeRMi3MluZM8Sd4kX5J\/H7MLJAWTQknhpEhSNCmWiosnJZKSSamkdFImKXtorwQAAAAAAAAAAAAAAAAAAAAAAAAAAAAAAAAAAAAAAAAAAAAAAAAAAAAAAAAAAAAAAAAAAAAAAAAAAAAA8M\/lq32Nr\/O1vv5wZwIAAIBD4d9UrrXU",
    "_version_": 6
}